{
  "$schema": "http://json-schema.org/draft-04/schema#",
  "$id": "https://www.jetbrains.com/guide/technology.schema.json",
  "title": "JetBrains Guide Technology",
  "properties": {
    "title": {
      "description": "Title of this resource",
      "type": "string"
    },
    "label": {
      "description": "Label of this resource",
      "type": "string"
    },
    "subtitle": {
      "description": "Subtitle of this resource",
      "type": "string"
    },
    "logo": {
      "type": "string"
    }
  },
  "type": "object",
  "required": [
    "title",
    "logo"
  ]
}